buildbot_profiler/VERSION
buildbot_profiler/__init__.py
buildbot_profiler/api.py
buildbot_profiler/app.py
buildbot_profiler/static/scripts.js
buildbot_profiler/static/scripts.js.map
buildbot_profiler/static/styles.css
buildbot_profiler/static/styles.css.map
buildbot_profiler-1.3.1.dist-info/LICENSE
buildbot_profiler-1.3.1.dist-info/METADATA
buildbot_profiler-1.3.1.dist-info/WHEEL
buildbot_profiler-1.3.1.dist-info/entry_points.txt
buildbot_profiler-1.3.1.dist-info/top_level.txt
buildbot_profiler-1.3.1.dist-info/RECORD
