Metadata-Version: 2.1
Name: buildbot-profiler
Version: 1.3.1
Summary: "Profiler for buildbot master and its UI"
Home-page: https://github.com/tardyp/buildbot_profiler
Author: Buildbot contributors
Author-email: devel@buildbot.net
License: GNU GPL
Platform: UNKNOWN
Requires-Dist: klein
Requires-Dist: psutil
